google_keep_tasks/__init__.py
google_keep_tasks/_compat.py
google_keep_tasks/auth.py
google_keep_tasks/cli.py
google_keep_tasks/exceptions.py
google_keep_tasks/items.py
google_keep_tasks/labels.py
google_keep_tasks/management.py
google_keep_tasks/notes.py
google_keep_tasks/utils.py
gkeep-1.0.1.dist-info/AUTHORS.rst
gkeep-1.0.1.dist-info/METADATA
gkeep-1.0.1.dist-info/WHEEL
gkeep-1.0.1.dist-info/entry_points.txt
gkeep-1.0.1.dist-info/pbr.json
gkeep-1.0.1.dist-info/top_level.txt
gkeep-1.0.1.dist-info/RECORD
