Metadata-Version: 2.1
Name: gkeep
Version: 1.0.1
Summary: Google Keep Command Line Interface (CLI)
Home-page: https://github.com/Nekmo/gkeep
Author: Nekmo
Author-email: contacto@nekmo.com
License: UNKNOWN
Download-URL: https://github.com/Nekmo/gkeep/archive/master.zip
Keywords: google,keep,tasks,google-keep
Platform: linux
Classifier: License :: OSI Approved :: MIT License
Classifier: Operating System :: POSIX :: Linux
Classifier: Programming Language :: Python :: 2.7
Classifier: Programming Language :: Python :: 2 :: Only
Classifier: Natural Language :: English
Classifier: Development Status :: 3 - Alpha
Provides: google_keep_tasks
License-File: AUTHORS.rst
Requires-Dist: gkeepapi (>=0.10.6)
Requires-Dist: click
